datatest/__init__.py
datatest/__main__.py
datatest/_excepthook.py
datatest/_normalize.py
datatest/_pandas_integration.py
datatest/_pytest_plugin.py
datatest/_utils.py
datatest/_working_directory.py
datatest/acceptances.py
datatest/case.py
datatest/differences.py
datatest/main.py
datatest/requirements.py
datatest/runner.py
datatest/validation.py
datatest/__past__/__init__.py
datatest/__past__/api00.py
datatest/__past__/api010.py
datatest/__past__/api06.py
datatest/__past__/api07.py
datatest/__past__/api07_comp.py
datatest/__past__/api07_diffs.py
datatest/__past__/api07_error.py
datatest/__past__/api07_sources.py
datatest/__past__/api08.py
datatest/__past__/api09.py
datatest/__past__/api_dev0.py
datatest/__past__/api_dev1.py
datatest/__past__/api_dev2.py
datatest/__past__/get_reader.py
datatest/__past__/load_csv.py
datatest/__past__/temptable.py
datatest/__past__/squint/__init__.py
datatest/__past__/squint/query.py
datatest/_compatibility/__init__.py
datatest/_compatibility/abc.py
datatest/_compatibility/builtins.py
datatest/_compatibility/contextlib.py
datatest/_compatibility/decimal.py
datatest/_compatibility/functools.py
datatest/_compatibility/itertools.py
datatest/_compatibility/statistics.py
datatest/_compatibility/textwrap.py
datatest/_compatibility/collections/__init__.py
datatest/_compatibility/collections/abc.py
datatest/_vendor/__init__.py
datatest/_vendor/get_reader.py
datatest/_vendor/load_csv.py
datatest/_vendor/predicate.py
datatest/_vendor/repeatingcontainer.py
datatest/_vendor/temptable.py
datatest/_vendor/squint/__init__.py
datatest/_vendor/squint/query.py
datatest-0.11.1.dist-info/AUTHORS
datatest-0.11.1.dist-info/LICENSE
datatest-0.11.1.dist-info/METADATA
datatest-0.11.1.dist-info/WHEEL
datatest-0.11.1.dist-info/entry_points.txt
datatest-0.11.1.dist-info/top_level.txt
datatest-0.11.1.dist-info/RECORD
